{
  "Products" : [
    {       
      "id" : 1,
     "Title": "Amazing spiderman",
     "Author": "Jack",
      "ISBN": "8888",
      "PublicationDate" :"19-05-2012",
      "Price": "58.00",
      "Genre": "Adventure",
      "Format": "Doc"
    
   },
     {       
      "id" : 2,
     "Title":"Man vs Wild",
     "Author": "Bear grylls",
      "ISBN": "5848",
      "PublicationDate" :"15-07-2015",
      "Price": "170.00",
      "Genre": "Adventure",
      "Format": "PDF"
    
   },
     {       
      "id" : 3,
     "Title": "MSD: The untold story",
     "Author": "Dhoni",
      "ISBN": "6778",
      "PublicationDate" :"05-08-2014",
      "Price": "199.00",
      "Genre": "Sports",
      "Format": "PDF"
    
   }
  ] 
}
